plothic/ParseAsy.py
plothic/ParseHiC.py
plothic/PlotBed.py
plothic/PlotHiC.py
plothic/PlotMTX.py
plothic/__init__.py
plothic/cli.py
plothic/logger.py
plothic-1.0.0.dist-info/LICENSE
plothic-1.0.0.dist-info/METADATA
plothic-1.0.0.dist-info/WHEEL
plothic-1.0.0.dist-info/entry_points.txt
plothic-1.0.0.dist-info/top_level.txt
plothic-1.0.0.dist-info/RECORD
