Metadata-Version: 2.1
Name: plothic
Version: 1.0.0
Summary: Plot Whole genome-wide Hi-C contact heatmap
Home-page: https://github.com/Jwindler/PlotHiC
Author: Zijie Jiang
Author-email: jzjlab@163.com
License: G
Classifier: Programming Language :: Python :: 3
Classifier: License :: OSI Approved :: GNU General Public License v3 (GPLv3)
Classifier: Operating System :: OS Independent
Requires-Python: >=3.10
License-File: LICENSE
Requires-Dist: numpy>=2.1.1
Requires-Dist: pandas>=2.2.3
Requires-Dist: matplotlib>=3.9.2
Requires-Dist: hic-straw>=1.3.1
Requires-Dist: scikit-learn>=1.5.2
Requires-Dist: scipy>=1.14.1
Requires-Dist: six>=1.16.0
